MANIFEST.in
README
setup.py
redsolutioncms.django_trusted_html.egg-info/PKG-INFO
redsolutioncms.django_trusted_html.egg-info/SOURCES.txt
redsolutioncms.django_trusted_html.egg-info/dependency_links.txt
redsolutioncms.django_trusted_html.egg-info/entry_points.txt
redsolutioncms.django_trusted_html.egg-info/not-zip-safe
redsolutioncms.django_trusted_html.egg-info/requires.txt
redsolutioncms.django_trusted_html.egg-info/top_level.txt
trustedhtml/__init__.py
trustedhtml/__init__.pyc
trustedhtml/beautifulsoup.py
trustedhtml/beautifulsoup.pyc
trustedhtml/classes.py
trustedhtml/classes.pyc
trustedhtml/fields.py
trustedhtml/fields.pyc
trustedhtml/handler.py
trustedhtml/importpath.py
trustedhtml/importpath.pyc
trustedhtml/models.py
trustedhtml/models.pyc
trustedhtml/settings.py
trustedhtml/settings.pyc
trustedhtml/signals.py
trustedhtml/signals.pyc
trustedhtml/tests.py
trustedhtml/tests.pyc
trustedhtml/urlfile.py
trustedhtml/utils.py
trustedhtml/utils.pyc
trustedhtml/widgets.py
trustedhtml/widgets.pyc
trustedhtml/management/__init__.py
trustedhtml/management/__init__.pyc
trustedhtml/management/commands/__init__.py
trustedhtml/management/commands/trusted_log.py
trustedhtml/redsolution_setup/__init__.py
trustedhtml/redsolution_setup/admin.py
trustedhtml/redsolution_setup/make.py
trustedhtml/redsolution_setup/models.py
trustedhtml/redsolution_setup/urls.py
trustedhtml/redsolution_setup/templates/trustedhtml/redsolutioncms/settings.pyt
trustedhtml/rules/__init__.py
trustedhtml/rules/__init__.pyc
trustedhtml/rules/css/__init__.py
trustedhtml/rules/css/__init__.pyc
trustedhtml/rules/css/box.py
trustedhtml/rules/css/box.pyc
trustedhtml/rules/css/colors.py
trustedhtml/rules/css/colors.pyc
trustedhtml/rules/css/consts.py
trustedhtml/rules/css/consts.pyc
trustedhtml/rules/css/custom.py
trustedhtml/rules/css/custom.pyc
trustedhtml/rules/css/fonts.py
trustedhtml/rules/css/fonts.pyc
trustedhtml/rules/css/generate.py
trustedhtml/rules/css/generate.pyc
trustedhtml/rules/css/grammar.py
trustedhtml/rules/css/grammar.pyc
trustedhtml/rules/css/page.py
trustedhtml/rules/css/page.pyc
trustedhtml/rules/css/syndata.py
trustedhtml/rules/css/syndata.pyc
trustedhtml/rules/css/tables.py
trustedhtml/rules/css/tables.pyc
trustedhtml/rules/css/text.py
trustedhtml/rules/css/text.pyc
trustedhtml/rules/css/ui.py
trustedhtml/rules/css/ui.pyc
trustedhtml/rules/css/values.py
trustedhtml/rules/css/values.pyc
